README.rst
setup.py
django_spaminspector.egg-info/PKG-INFO
django_spaminspector.egg-info/SOURCES.txt
django_spaminspector.egg-info/dependency_links.txt
django_spaminspector.egg-info/not-zip-safe
django_spaminspector.egg-info/requires.txt
django_spaminspector.egg-info/top_level.txt
spaminspector/__init__.py
spaminspector/middleware.py
spaminspector_test/src/spaminspector_test/__init__.py
spaminspector_test/src/spaminspector_test/manage.py
spaminspector_test/src/spaminspector_test/settings.py
spaminspector_test/src/spaminspector_test/urls.py
spaminspector_test/src/spaminspector_test/blogs/__init__.py
spaminspector_test/src/spaminspector_test/blogs/admin.py
spaminspector_test/src/spaminspector_test/blogs/models.py
spaminspector_test/src/spaminspector_test/blogs/urls.py
spaminspector_test/src/spaminspector_test/blogs/fixtures/initial_data.json
spaminspector_test/templates/base.html
spaminspector_test/templates/spam.html
spaminspector_test/templates/blogs/entry_detail.html
spaminspector_test/templates/blogs/entry_list.html