Metadata-Version: 1.0
Name: django-spaminspector
Version: 0.1rc4
Summary: django-spaminspector is a generic spam inspector of Django via Akismet
Home-page: https://github.com/lambdalisue/django-spaminspector
Author: Alisue
Author-email: lambdalisue@hashnote.net
License: BSD
Download-URL: https://github.com/lambdalisue/django-spaminspector/tarball/master
Keywords: django generic spam inspector filtering akismet
Platform: UNKNOWN
Classifier: Framework :: Django
Classifier: Intended Audience :: Developers
Classifier: License :: OSI Approved :: BSD License
Classifier: Programming Language :: Python
Classifier: Topic :: Internet :: WWW/HTTP
